{
  "task_id": "S1BI1",
  "task_name": "데이터베이스 및 설정 인프라 구축",
  "stage": 1,
  "area": "BI",
  "level": 2,
  "task_status": "Completed",
  "task_progress": 100,
  "dependencies": "",
  "task_instruction": "task-instructions/S1BI1_instruction.md",
  "task_agent": "backend-developer",
  "generated_files": "package.json, next.config.js, tsconfig.json, tailwind.config.ts, postcss.config.mjs, lib/supabase/client.ts, lib/supabase/server.ts, lib/supabase/middleware.ts, .env.local, .env.local.example, lib/config.ts, middleware.ts, types/database.types.ts, app/globals.css, app/layout.tsx, app/page.tsx, node_modules/",
  "duration": "약 10분",
  "build_result": "성공 - Next.js 개발 서버 실행 중 (localhost:3000)",
  "verification_instruction": "verification-instructions/S1BI1_verification.md",
  "verification_agent": "code-reviewer",
  "verification_status": "Verified",
  "test_result": {
    "file_existence": "PASS - 12/12 files exist",
    "supabase_client": "PASS - createBrowserClient, createServerClient imports",
    "middleware": "PASS - updateSession function with cookie handling",
    "config": "PASS - Environment variable validation"
  },
  "build_verification": {
    "compile": "PASS - TypeScript types correct",
    "lint": "PASS - No ESLint errors",
    "syntax": "PASS - Valid TypeScript/JSX",
    "deploy": "READY - Vercel deployment ready"
  },
  "integration_verification": {
    "dependency_propagation": "PASS - No dependencies required",
    "cross_task_connection": "PASS - S1D1, S2BA1, S2F7 can use Supabase client",
    "data_flow": "PASS - Client -> Middleware -> Server flow correct"
  },
  "blockers": {
    "status": "No Blockers",
    "details": []
  },
  "comprehensive_verification": {
    "task_instruction": "PASS",
    "test": "PASS 4/4",
    "build": "PASS 4/4",
    "integration": "PASS 3/3",
    "blockers": "None",
    "final": "Passed"
  },
  "ai_verification_note": "S1BI1 검증 완료. Next.js 14 프로젝트 초기화, Supabase SSR 클라이언트 3종(client/server/middleware), 환경 설정, 타입 정의 파일 모두 확인됨. node_modules에 @supabase/ssr, @supabase/supabase-js 설치 완료. S1D1 완료 후 types/database.types.ts 업데이트 필요.",
  "stage_gate_status": "Conditional Pass",
  "remarks": "Supabase 클라이언트 및 환경 설정",
  "created_at": "2026-02-06",
  "updated_at": "2026-02-07",
  "tools": [
    "Read",
    "Write",
    "Bash"
  ],
  "execution_type": "Human-AI"
}